MANIFEST.in
README.rst
pythonbrew_install.py
setup.py
pythonbrew/__init__.py
pythonbrew/basecommand.py
pythonbrew/baseparser.py
pythonbrew/curl.py
pythonbrew/define.py
pythonbrew/downloader.py
pythonbrew/exceptions.py
pythonbrew/log.py
pythonbrew/util.py
pythonbrew.egg-info/PKG-INFO
pythonbrew.egg-info/SOURCES.txt
pythonbrew.egg-info/dependency_links.txt
pythonbrew.egg-info/entry_points.txt
pythonbrew.egg-info/not-zip-safe
pythonbrew.egg-info/top_level.txt
pythonbrew/commands/__init__.py
pythonbrew/commands/buildout.py
pythonbrew/commands/cleanup.py
pythonbrew/commands/help.py
pythonbrew/commands/install.py
pythonbrew/commands/list.py
pythonbrew/commands/off.py
pythonbrew/commands/py.py
pythonbrew/commands/switch.py
pythonbrew/commands/symlink.py
pythonbrew/commands/uninstall.py
pythonbrew/commands/update.py
pythonbrew/commands/use.py
pythonbrew/commands/venv.py
pythonbrew/commands/version.py
pythonbrew/etc/bashrc
pythonbrew/etc/config.cfg
pythonbrew/etc/pythonbrew.fish
pythonbrew/installer/__init__.py
pythonbrew/installer/pythonbrewinstaller.py
pythonbrew/installer/pythoninstaller.py
pythonbrew/patches/all/common/patch-setup.py.diff
pythonbrew/patches/all/python24/patch-setup.py.diff
pythonbrew/patches/all/python25/patch-setup.py.diff
pythonbrew/patches/all/python26/patch-Makefile.pre.in-for-2.6.2-and-earlier.diff
pythonbrew/patches/all/python26/patch-_ssl.c-for-ubuntu-oneiric-and-later.diff
pythonbrew/patches/all/python26/patch-setup.py-for-2.6.5-and-earlier.diff
pythonbrew/patches/all/python27/patch-Modules-_sqlite-connection.c.diff
pythonbrew/patches/all/python27/patch-Modules-_sqlite-for-2.7.4.diff
pythonbrew/patches/all/python30/patch-setup.py.diff
pythonbrew/patches/all/python32/patch-setup.py.diff
pythonbrew/patches/macosx/python24/patch-Include-pyport.h
pythonbrew/patches/macosx/python24/patch-Lib-cgi.py.diff
pythonbrew/patches/macosx/python24/patch-Lib-site.py.diff
pythonbrew/patches/macosx/python24/patch-Mac-OSX-IDLE-Makefile.in
pythonbrew/patches/macosx/python24/patch-Mac-OSX-Makefile.in
pythonbrew/patches/macosx/python24/patch-Mac-OSX-PythonLauncher-Makefile.in
pythonbrew/patches/macosx/python24/patch-Makefile.pre.in
