Metadata-Version: 1.1
Name: pythonbrew
Version: 1.3.6
Summary: Manage python installations in your $HOME
Home-page: https://github.com/utahta/pythonbrew
Author: utahta
Author-email: labs.ninxit@gmail.com
License: MIT
Keywords: pythonbrew pip easy_install distutils setuptools virtualenv
Platform: UNKNOWN
Classifier: Development Status :: 5 - Production/Stable
Classifier: Intended Audience :: Developers
Classifier: License :: OSI Approved :: MIT License
Classifier: Topic :: Software Development :: Build Tools
Classifier: Programming Language :: Python :: 2.4
Classifier: Programming Language :: Python :: 2.5
Classifier: Programming Language :: Python :: 2.6
Classifier: Programming Language :: Python :: 2.7
Classifier: Programming Language :: Python :: 3
Classifier: Programming Language :: Python :: 3.1
Classifier: Programming Language :: Python :: 3.2
Classifier: Programming Language :: Python :: 3.3
Classifier: Programming Language :: Python :: 3.4
